capfit/CHANGELOG.rst
capfit/LICENSE.txt
capfit/README.rst
capfit/__init__.py
capfit/capfit.py
capfit/format_values_with_errors.py
capfit/examples/__init__.py
capfit/examples/capfit_examples.py
capfit/examples/capfit_reference_output.txt
capfit-2.7.1.dist-info/METADATA
capfit-2.7.1.dist-info/WHEEL
capfit-2.7.1.dist-info/top_level.txt
capfit-2.7.1.dist-info/zip-safe
capfit-2.7.1.dist-info/RECORD
