Metadata-Version: 2.4
Name: capfit
Version: 2.7.1
Summary: CapFit: linearly-constrained non-linear least-squares optimization
Home-page: https://purl.org/cappellari/software
Author: Michele Cappellari
Author-email: michele.cappellari@physics.ox.ac.uk
License: Other/Proprietary License
Classifier: Development Status :: 5 - Production/Stable
Classifier: Intended Audience :: Developers
Classifier: Intended Audience :: Science/Research
Classifier: Operating System :: OS Independent
Classifier: Programming Language :: Python :: 3
Requires-Dist: numpy
Requires-Dist: scipy
Dynamic: author
Dynamic: author-email
Dynamic: classifier
Dynamic: description
Dynamic: description-content-type
Dynamic: home-page
Dynamic: license
Dynamic: requires-dist
Dynamic: summary
